LICENSE.txt
MANIFEST.in
README.rst
mailman-hyperkitty.cfg
mailman3-hyperkitty.spec
setup.py
unittest.cfg
mailman_hyperkitty/__init__.py
mailman_hyperkitty.egg-info/PKG-INFO
mailman_hyperkitty.egg-info/SOURCES.txt
mailman_hyperkitty.egg-info/dependency_links.txt
mailman_hyperkitty.egg-info/requires.txt
mailman_hyperkitty.egg-info/top_level.txt
mailman_hyperkitty/tests/__init__.py
mailman_hyperkitty/tests/test_archiver.py