Metadata-Version: 1.1
Name: mailman-hyperkitty
Version: 1.2.0
Summary: Mailman archiver plugin for HyperKitty
Home-page: https://gitlab.com/mailman/mailman-hyperkitty/
Author: HyperKitty Developers
Author-email: hyperkitty-devel@lists.fedorahosted.org
License: GPLv3
Keywords: email
Platform: UNKNOWN
Classifier: Development Status :: 4 - Beta
Classifier: License :: OSI Approved :: GNU General Public License v3 (GPLv3)
Classifier: Topic :: Communications :: Email :: Mailing List Servers
Classifier: Programming Language :: Python :: 3
